README.md
setup.cfg
setup.py
gnome_station_analysis/__init__.py
gnome_station_analysis/fit.py
gnome_station_analysis/functions.py
gnome_station_analysis/read.py
gnome_station_analysis/resonances.py
gnome_station_analysis.egg-info/PKG-INFO
gnome_station_analysis.egg-info/SOURCES.txt
gnome_station_analysis.egg-info/dependency_links.txt
gnome_station_analysis.egg-info/requires.txt
gnome_station_analysis.egg-info/top_level.txt