Metadata-Version: 2.1
Name: gnome-station-analysis
Version: 0.1.4
Summary: GNOME Station Analysis Tools
Home-page: https://github.com/gregorylukasiewicz/gnome_station_analysis
Author: GNOME team in Kraków
Author-email: gregory.lukasiewicz@gmail.com
License: MIT
Download-URL: https://github.com/gregorylukasiewicz/gnome_station_analysis/archive/refs/tags/v_0.1.3.tar.gz
Platform: UNKNOWN
Requires-Python: >=3.8
